main.py
shomoy-0.1.0.dist-info/licenses/LICENSE
shomoy-0.1.0.dist-info/METADATA
shomoy-0.1.0.dist-info/WHEEL
shomoy-0.1.0.dist-info/top_level.txt
shomoy-0.1.0.dist-info/RECORD
