Metadata-Version: 2.4
Name: Shomoy
Version: 0.1.0
Summary: A time capsule for your terminal
Requires-Python: >=3.13
License-File: LICENSE
Requires-Dist: cryptography>=46.0.3
Requires-Dist: rich>=14.2.0
Requires-Dist: tinydb>=4.8.2
Dynamic: license-file
